{
 "file": "Meetings.bb",
 "functions": [
  {
   "name": "RiskFormalMeetings",
   "args": "",
   "line": 8,
   "calls": [
    "charFed",
    "fedBooker",
    "fedBank",
    "charExperience",
    "fedRanked",
    "fedSize",
    "gamSchedule",
    "gamAgreement",
    "fedRoster",
    "charPopularity",
    "charStrength",
    "charSkill",
    "charAgility",
    "charStamina",
    "charToughness",
    "charGender",
    "fedPopularity",
    "fedReputation",
    "CountProductions",
    "showRanked",
    "showOldRanked",
    "fedChampWorld",
    "fedChampInter",
    "TitleHolder",
    "fedProduction",
    "Meeting"
   ],
   "doc": ""
  },
  {
   "name": "RiskCasualMeetings",
   "args": "factor",
   "line": 128,
   "calls": [
    "charFed",
    "fedSize",
    "fedRoster",
    "gamNegotiated",
    "charVacant",
    "InjuryStatus",
    "charHeel",
    "AllegianceRatio",
    "TitleHolder",
    "charAgreement",
    "fedChampWorld",
    "fedChampInter",
    "fedChampTag",
    "charPartner",
    "FindFriend",
    "FindRealFriend",
    "charManager",
    "gamSchedule",
    "gamSegments",
    "FindRealEnemy",
    "Or",
    "charLegs",
    "fedProduction",
    "CountProductions",
    "charTrainCourse",
    "AverageStats",
    "charHealth",
    "charWorked",
    "MajorLimb",
    "charLimb",
    "charAttitude",
    "charHappiness",
    "charSalary",
    "charContract",
    "Meeting"
   ],
   "doc": ""
  },
  {
   "name": "PostMatchMeetings",
   "args": "",
   "line": 231,
   "calls": [
    "charFed",
    "pChar",
    "InjuryStatus",
    "charVacant",
    "charRelationship",
    "pRole",
    "pTeam",
    "charPartner",
    "charManager",
    "TitleHolder",
    "Or",
    "pAbused",
    "charRole",
    "pIntruder",
    "gamSchedule",
    "gamSegments",
    "fedBooker",
    "gamRivalFed",
    "fedBank",
    "Meeting"
   ],
   "doc": ""
  },
  {
   "name": "PrepareMeeting",
   "args": "",
   "line": 329,
   "calls": [
    "ResetTextures",
    "pChar",
    "fedBooker",
    "FindCharacter",
    "charFed",
    "And",
    "LoadAnimMesh",
    "LoadTexture",
    "FindChild",
    "GetArenaSettings",
    "gamVenue",
    "DecorateArena",
    "tCrowd",
    "sCrowd",
    "PlaySound",
    "PrepareScenery",
    "CreateCamera",
    "GraphicsWidth",
    "GraphicsHeight",
    "CreatePivot",
    "light",
    "CreateLight",
    "gamAgreement",
    "Or",
    "pAnim",
    "EntityX",
    "EntityZ",
    "LoadMeeter",
    "RestoreTextures"
   ],
   "doc": ""
  },
  {
   "name": "LoadMeeter",
   "args": "cyc,char",
   "line": 554,
   "calls": [
    "p",
    "LoadAnimMesh",
    "GetModel",
    "StripModel",
    "pCostume",
    "ApplyCostume",
    "pEyes",
    "pOldEyes",
    "pFoc",
    "TitleHolder",
    "WearBelt",
    "gamSegments",
    "FindCharacter",
    "pLimb",
    "tFaceScar",
    "tBodyScar",
    "Or",
    "tArmScar",
    "tHandScar",
    "tLegScar",
    "tEyeScar",
    "pSeq",
    "LoadAnimSeq",
    "ExtractAnimSeq",
    "pAnim",
    "charGender",
    "pChar",
    "InjuryStatus",
    "charHealth",
    "charFed",
    "fedBooker",
    "pState",
    "charHeight",
    "LoadShadows"
   ],
   "doc": ""
  },
  {
   "name": "Meeting",
   "args": "",
   "line": 642,
   "calls": [
    "Loader",
    "CopyChar",
    "charPartner",
    "charBaggy",
    "charHatStyle",
    "charHat",
    "charSpecs",
    "charBody",
    "charLeftArm",
    "charRightArm",
    "charLeftForearm",
    "charRightForearm",
    "charLeftHand",
    "charRightHand",
    "charShorts",
    "charLegs",
    "charShins",
    "charShoes",
    "Until",
    "GetRace",
    "charHair",
    "charHairStyle",
    "fedRoster",
    "fedSize",
    "charPopularity",
    "fedPopularity",
    "TitleHolder",
    "charVacant",
    "InjuryStatus",
    "gamSchedule",
    "PrepareMeeting",
    "fedChampWorld",
    "fedChampInter",
    "FindStrength",
    "FindFriend",
    "FindRealFriend",
    "FindRealEnemy",
    "charRealRelationship",
    "charFed",
    "ImportantChar"
   ],
   "doc": ""
  },
  {
   "name": "AdjustAttitude",
   "args": "char,level",
   "line": 3945,
   "calls": [
    "charAttitude",
    "charHappiness",
    "charOldHappiness",
    "charOldAttitude"
   ],
   "doc": ""
  },
  {
   "name": "RandomizeAnimation",
   "args": "cyc",
   "line": 3959,
   "calls": [
    "pAnim",
    "pSpeaking",
    "pOldAnim",
    "p",
    "pSeq"
   ],
   "doc": ""
  }
 ],
 "types": [],
 "globals": [],
 "consts": [],
 "dims": [],
 "lineCount": 3981
}